joj_auth/__init__.py
joj_auth/__main__.py
joj_auth/command_line.py
joj_auth/joj.py
joj_auth/login.py
joj_auth-0.0.3.dist-info/LICENSE
joj_auth-0.0.3.dist-info/METADATA
joj_auth-0.0.3.dist-info/WHEEL
joj_auth-0.0.3.dist-info/entry_points.txt
joj_auth-0.0.3.dist-info/top_level.txt
joj_auth-0.0.3.dist-info/RECORD
